README.rst
setup.cfg
setup.py
zerorm/__init__.py
zerorm/models.py
zerorm.egg-info/PKG-INFO
zerorm.egg-info/SOURCES.txt
zerorm.egg-info/dependency_links.txt
zerorm.egg-info/requires.txt
zerorm.egg-info/top_level.txt