Metadata-Version: 1.1
Name: zerorm
Version: 0.2.0
Summary: Looks like ORM and stores your data
Home-page: https://github.com/hedin/zerorm
Author: Aleksandr Mironov
Author-email: a.m.mironov@gmail.com
License: MIT
Platform: UNKNOWN
Classifier: Development Status :: 3 - Alpha
Classifier: License :: OSI Approved :: MIT License
Classifier: Operating System :: POSIX
Classifier: Programming Language :: Python :: 3.5
Classifier: Programming Language :: Python :: 3.6
Classifier: Topic :: Database
Classifier: Topic :: Software Development :: Libraries :: Python Modules
Classifier: Intended Audience :: Developers
